distro/__init__.py
distro/__main__.py
distro/data.py
distro/distro.py
distro_names-0.0.8.dist-info/entry_points.txt
distro_names-0.0.8.dist-info/LICENSE.txt
distro_names-0.0.8.dist-info/WHEEL
distro_names-0.0.8.dist-info/METADATA
distro_names-0.0.8.dist-info/RECORD
