Metadata-Version: 2.1
Name: distro-names
Version: 0.0.8
Summary: Search for the names and versions of popular OS distributions
Home-page: https://github.com/igorlg/distro-names
License: MIT-0
Author: Igor Gentil
Author-email: igorlg@amazon.com
Requires-Python: >=3.6,<4.0
Classifier: Development Status :: 5 - Production/Stable
Classifier: License :: OSI Approved :: MIT License
Classifier: License :: Other/Proprietary License
Classifier: Natural Language :: English
Classifier: Programming Language :: Python :: 3
Classifier: Programming Language :: Python :: 3.6
Classifier: Programming Language :: Python :: 3.7
Classifier: Programming Language :: Python :: 3.8
Classifier: Programming Language :: Python :: 3.9
Project-URL: Repository, https://github.com/igorlg/distro-names
